phenoqc/__init__.py
phenoqc/__main__.py
phenoqc/batch_processing.py
phenoqc/cli.py
phenoqc/configuration.py
phenoqc/input.py
phenoqc/logging_module.py
phenoqc/mapping.py
phenoqc/missing_data.py
phenoqc/quality_metrics.py
phenoqc/reporting.py
phenoqc/validation.py
phenoqc/gui/__init__.py
phenoqc/gui/gui.py
phenoqc/gui/views.py
phenoqc/utils/__init__.py
phenoqc/utils/ontology_utils.py
phenoqc/utils/zip_utils.py
phenoqc-1.2.1.dist-info/licenses/LICENSE
phenoqc-1.2.1.dist-info/METADATA
phenoqc-1.2.1.dist-info/WHEEL
phenoqc-1.2.1.dist-info/entry_points.txt
phenoqc-1.2.1.dist-info/top_level.txt
phenoqc-1.2.1.dist-info/RECORD
