Metadata-Version: 2.4
Name: phenoqc
Version: 1.2.1
Summary: Phenotypic Data Quality Control Toolkit for Genomic Data Infrastructure (GDI)
Home-page: https://github.com/jorgeMFS/PhenoQC
Author: Jorge Miguel Ferreira da Silva
License: MIT License
Project-URL: Homepage, https://github.com/jorgeMFS/PhenoQC
Project-URL: Repository, https://github.com/jorgeMFS/PhenoQC.git
Project-URL: Documentation, https://phenoqc.readthedocs.io/en/latest/
Project-URL: Issues, https://github.com/jorgeMFS/PhenoQC/issues
Classifier: Programming Language :: Python :: 3
Classifier: Programming Language :: Python :: 3.9
Classifier: License :: OSI Approved :: MIT License
Classifier: Operating System :: OS Independent
Classifier: Intended Audience :: Science/Research
Classifier: Topic :: Scientific/Engineering :: Bio-Informatics
Requires-Python: >=3.9
License-File: LICENSE
Requires-Dist: pandas
Requires-Dist: jsonschema
Requires-Dist: requests
Requires-Dist: plotly
Requires-Dist: reportlab
Requires-Dist: streamlit
Requires-Dist: pyyaml
Requires-Dist: kaleido>=0.1.0
Requires-Dist: tqdm
Requires-Dist: Pillow
Requires-Dist: scikit-learn
Requires-Dist: fancyimpute
Requires-Dist: fastjsonschema
Requires-Dist: pronto
Requires-Dist: psutil
Requires-Dist: rapidfuzz
Requires-Dist: streamlit-aggrid
Requires-Dist: ucimlrepo
Provides-Extra: test
Requires-Dist: pytest; extra == "test"
Dynamic: home-page
Dynamic: license-file
Dynamic: requires-python
